spadsampler/__init__.py
spadsampler/spadsampler.py
spadsampler-0.1.6.dist-info/METADATA
spadsampler-0.1.6.dist-info/WHEEL
spadsampler-0.1.6.dist-info/licenses/LICENSE
spadsampler-0.1.6.dist-info/RECORD
