Metadata-Version: 2.3
Name: spadsampler
Version: 0.1.6
Summary: A library for creating binomial sampled data mimicking SPAD images.
Author-email: Yehe Liu <yehe@case.edu>
License: CC0 1.0 Universal (CC0 1.0) Public Domain Dedication
License-File: LICENSE
Classifier: Development Status :: 3 - Alpha
Classifier: Intended Audience :: Developers
Classifier: License :: CC0 1.0 Universal (CC0 1.0) Public Domain Dedication
Classifier: Operating System :: OS Independent
Classifier: Programming Language :: Python :: 3
Classifier: Programming Language :: Python :: 3.10
Classifier: Programming Language :: Python :: 3.11
Classifier: Programming Language :: Python :: 3.12
Requires-Python: >=3.10
Requires-Dist: lazyimread
Requires-Dist: matplotlib
Requires-Dist: tqdm
Provides-Extra: dev
Requires-Dist: pre-commit; extra == 'dev'
Requires-Dist: pytest; extra == 'dev'
Requires-Dist: ruff; extra == 'dev'
Requires-Dist: tox; extra == 'dev'
